corentin_regent_test/__init__.py
corentin_regent_test/_main.py
corentin_regent_test/py.typed
corentin_regent_test-1.0.1.dist-info/LICENSE
corentin_regent_test-1.0.1.dist-info/METADATA
corentin_regent_test-1.0.1.dist-info/WHEEL
corentin_regent_test-1.0.1.dist-info/RECORD
