Metadata-Version: 2.1
Name: corentin-regent-test
Version: 1.0.1
Summary: Cool project built with Tempoet
Home-page: https://github.com/corentin-regent/corentin-regent-test
License: MIT
Author: Corentin Régent
Author-email: corentin.regent.pro@gmail.com
Requires-Python: >=3.8,<4.0
Classifier: Development Status :: 2 - Pre-Alpha
Classifier: License :: OSI Approved :: MIT License
Classifier: Programming Language :: Python
Classifier: Programming Language :: Python :: 3
Classifier: Programming Language :: Python :: 3.8
Classifier: Programming Language :: Python :: 3.9
Classifier: Programming Language :: Python :: 3.10
Classifier: Programming Language :: Python :: 3.11
Classifier: Programming Language :: Python :: 3.12
Classifier: Typing :: Typed
Project-URL: Changelog, https://corentin-regent.github.io/corentin-regent-test/changelog.html
